ai_search_api/__init__.py
ai_search_api/ai_search.py
ai_search_api/database.py
ai_search_api/error.py
ai_search_api/local.py
ai_search_api/test.py
ai_search_api/update.py
ai_search_api/update_database.py
ai_search_api/withUI.py
ai_search_api/withui.py
ai_search_api-0.0.8.2.9.1.dist-info/LICENSE
ai_search_api-0.0.8.2.9.1.dist-info/METADATA
ai_search_api-0.0.8.2.9.1.dist-info/WHEEL
ai_search_api-0.0.8.2.9.1.dist-info/top_level.txt
ai_search_api-0.0.8.2.9.1.dist-info/RECORD
