Metadata-Version: 2.1
Name: ai-search-api
Version: 0.0.8.2.9.1
Summary: search the future [test version]
Home-page: https://github.com/neopad/ai-search
Author: NeopadAI
Author-email: neopad.azienda@gmail.com
Classifier: Programming Language :: Python :: 3
Classifier: License :: OSI Approved :: MIT License
Classifier: Operating System :: OS Independent
License-File: LICENSE
